rovpp/__init__.py
rovpp/__main__.py
rovpp/rovpp_ann.py
rovpp/as_classes/__init__.py
rovpp/as_classes/non_lite.py
rovpp/as_classes/rovpp_v3_as.py
rovpp/as_classes/v1/__init__.py
rovpp/as_classes/v1/rovpp_v1_lite_simple_as.py
rovpp/as_classes/v1/rovpp_v1_simple_as.py
rovpp/as_classes/v2/__init__.py
rovpp/as_classes/v2/v2_aggressive/__init__.py
rovpp/as_classes/v2/v2_aggressive/rovpp_v2a_lite_simple_as.py
rovpp/as_classes/v2/v2_aggressive/rovpp_v2a_simple_as.py
rovpp/as_classes/v2/v2_base/__init__.py
rovpp/as_classes/v2/v2_base/rovpp_v2_lite_simple_as.py
rovpp/as_classes/v2/v2_base/rovpp_v2_simple_as.py
rovpp/as_classes/v2/v2_base_shorten/__init__.py
rovpp/as_classes/v2/v2_base_shorten/_copy_and_process.py
rovpp/as_classes/v2/v2_base_shorten/rovpp_v2_shorten_lite_simple_as.py
rovpp/as_classes/v2/v2_base_shorten/rovpp_v2_shorten_simple_as.py
rovpp/as_classes/v2/v2_journal/__init__.py
rovpp/as_classes/v2/v2_journal/rovpp_v2_journal_lite_simple_as.py
rovpp/as_classes/v2/v2_journal/rovpp_v2_journal_simple_as.py
rovpp/custom_graphs/__init__.py
rovpp/custom_graphs/ctrl_vs_data_graph.py
rovpp/custom_graphs/lite_graph.py
rovpp/tests/__init__.py
rovpp/tests/conftest.py
rovpp/tests/test_main.py
rovpp/tests/engine_tests/__init__.py
rovpp/tests/engine_tests/test_engine.py
rovpp/tests/engine_tests/engine_test_configs/__init__.py
rovpp/tests/engine_tests/engine_test_configs/config_035.py
rovpp/tests/engine_tests/engine_test_configs/config_036.py
rovpp/tests/engine_tests/engine_test_configs/config_037.py
rovpp/tests/engine_tests/engine_test_configs/config_038.py
rovpp/tests/engine_tests/engine_test_configs/config_039.py
rovpp/tests/engine_tests/engine_test_configs/config_040.py
rovpp/tests/engine_tests/engine_test_configs/config_041.py
rovpp/tests/engine_tests/engine_test_configs/config_042.py
rovpp/tests/engine_tests/engine_test_configs/config_043.py
rovpp/tests/engine_tests/engine_test_configs/config_044.py
rovpp/tests/engine_tests/engine_test_configs/config_045.py
rovpp-1.17.0.dist-info/LICENSE.txt
rovpp-1.17.0.dist-info/METADATA
rovpp-1.17.0.dist-info/WHEEL
rovpp-1.17.0.dist-info/entry_points.txt
rovpp-1.17.0.dist-info/top_level.txt
rovpp-1.17.0.dist-info/RECORD
