Metadata-Version: 2.1
Name: rovpp
Version: 1.17.0
Summary: Simulates ROV++
Home-page: https://github.com/jfuruness/rovpp
Author: Justin Furuness
Author-email: jfuruness@gmail.com
License: BSD
Keywords: BGP,Caida,Peers,Providers,Relationships,AS-Serial,Customers,Simulation,ROV,ROV++,Furuness
Classifier: Programming Language :: Python :: 3
Classifier: Environment :: Console
Classifier: License :: OSI Approved :: BSD License
Classifier: Intended Audience :: Developers
Requires-Python: >=3.10
License-File: LICENSE.txt
Requires-Dist: bgpy-pkg ==1.21.1
Requires-Dist: graphviz ==0.20
Requires-Dist: pillow ==9.2.0
Requires-Dist: matplotlib ==3.5.2
Requires-Dist: pytest ==7.1.2
Requires-Dist: tqdm ==4.64.0
Requires-Dist: yamlable ==1.1.1
Provides-Extra: test
Requires-Dist: pytest-cov ==3.0.0 ; extra == 'test'
Requires-Dist: black ==23.7.0 ; extra == 'test'
Requires-Dist: pre-commit ==3.3.3 ; extra == 'test'
Requires-Dist: types-requests ==2.31.0 ; extra == 'test'
Requires-Dist: types-PyYAML ==6.0.11 ; extra == 'test'
Requires-Dist: mypy ==0.982 ; extra == 'test'
Requires-Dist: flake8 ==4.0.1 ; extra == 'test'
Requires-Dist: tox ==4.6.3 ; extra == 'test'
Requires-Dist: pytest-xdist ==2.5.0 ; extra == 'test'
Requires-Dist: ruff ==0.0.275 ; extra == 'test'
